{
  "tokens": [
    {
      "token": "8000"
    },
    {
      "token": "8001"
    },
    {
      "token": "8002"
    },
    {
      "token": "8003"
    },
    {
      "token": "8004"
    },
    {
      "token": "8005"
    },
    {
      "token": "8006"
    },
    {
      "token": "8007"
    },{
      "token": "8008"
    },{
      "token": "8009"
    },
    {
      "token": "8010"
    },
    {
      "token": "8011"
    },
    {
      "token": "8012"
    },
    {
      "token": "8013"
    },
    {
      "token": "8014"
    },
    {
      "token": "8015"
    },
    {
      "token": "8016"
    },
    {
      "token": "8017"
    },{
      "token": "8018"
    },{
      "token": "8019"
    }

  ]
}